local_llm_cli/__init__.py
local_llm_cli/converse/__init__.py
local_llm_cli/converse/chat.py
local_llm_cli-0.1.3.dist-info/METADATA
local_llm_cli-0.1.3.dist-info/WHEEL
local_llm_cli-0.1.3.dist-info/top_level.txt
local_llm_cli-0.1.3.dist-info/RECORD
