Metadata-Version: 2.1
Name: local-llm-cli
Version: 0.1.3
Summary: Converse with GPT4 LLM locally
Author: Harsh Avinash
Author-email: harsh.avinash.official@gmail.com
Classifier: Programming Language :: Python :: 3
Classifier: License :: OSI Approved :: MIT License
Classifier: Operating System :: OS Independent
Requires-Dist: langchain
Requires-Dist: python-dotenv
